agentape/__init__.py
agentape/exceptions.py
agentape/pytest_plugin.py
agentape/clients/__init__.py
agentape/clients/base.py
agentape/clients/openai_client.py
agentape/core/__init__.py
agentape/core/context.py
agentape/core/matching.py
agentape/core/recorder.py
agentape/core/registry.py
agentape/core/replayer.py
agentape/core/tape.py
agentape/storage/__init__.py
agentape/storage/yaml_storage.py
agentape-0.1.0.dist-info/METADATA
agentape-0.1.0.dist-info/WHEEL
agentape-0.1.0.dist-info/entry_points.txt
agentape-0.1.0.dist-info/licenses/LICENSE
agentape-0.1.0.dist-info/RECORD
