Metadata-Version: 2.4
Name: agentape
Version: 0.1.0
Summary: Record/replay testing for LLM agents - VCR.py but for LLM SDKs
Project-URL: Homepage, https://github.com/agentape/agentape
Project-URL: Documentation, https://github.com/agentape/agentape#readme
Project-URL: Repository, https://github.com/agentape/agentape
Project-URL: Issues, https://github.com/agentape/agentape/issues
Author: agentape contributors
License-Expression: MIT
License-File: LICENSE
Keywords: anthropic,llm,openai,record,replay,testing,vcr
Classifier: Development Status :: 3 - Alpha
Classifier: Intended Audience :: Developers
Classifier: License :: OSI Approved :: MIT License
Classifier: Programming Language :: Python :: 3
Classifier: Programming Language :: Python :: 3.10
Classifier: Programming Language :: Python :: 3.11
Classifier: Programming Language :: Python :: 3.12
Classifier: Topic :: Software Development :: Testing
Requires-Python: >=3.10
Requires-Dist: openai>=1.0.0
Requires-Dist: python-dotenv>=1.0.0
Requires-Dist: pyyaml>=6.0
Provides-Extra: anthropic
Requires-Dist: anthropic>=0.18.0; extra == 'anthropic'
Provides-Extra: dev
Requires-Dist: mypy; extra == 'dev'
Requires-Dist: pytest-asyncio; extra == 'dev'
Requires-Dist: pytest>=7.0; extra == 'dev'
Requires-Dist: ruff; extra == 'dev'
Requires-Dist: types-pyyaml; extra == 'dev'
Provides-Extra: semantic
Requires-Dist: numpy; extra == 'semantic'
Requires-Dist: openai; extra == 'semantic'
